[
    {
        "tweet": {
            "id": 17680161897971712,
            "creation_date": "2010-12-22 20:37:33",
            "search_type": "User",
            "search_string": "capitao_augusto",
            "like_number": 10,
            "tweet_source": null,
            "rendered_content": "ABANDONO: Líderes sepultam votação da PEC 300 http://capitaoaugusto.com.br"
        }
    },
    {
        "tweet": {
            "id": 13918967248723968,
            "creation_date": "2010-12-12 11:31:55",
            "search_type": "User",
            "search_string": "capitao_augusto",
            "like_number": 8,
            "tweet_source": null,
            "rendered_content": "Bom domingo a todos, acessem o site: http://www.partidomilitarbrasileiro.com.br a reserva moral do Brasil"
        }
    },
    {
        "tweet": {
            "id": 11028516271300609,
            "creation_date": "2010-12-04 12:06:17",
            "search_type": "User",
            "search_string": "capitao_augusto",
            "like_number": 17,
            "tweet_source": null,
            "rendered_content": "Nem tudo esta perdito, ainda existem Militares: http://www.partidomilitarbrasileiro.com.br"
        }
    },
    {
        "tweet": {
            "id": 2844974039171073,
            "creation_date": "2010-11-11 22:07:49",
            "search_type": "User",
            "search_string": "capitao_augusto",
            "like_number": 3,
            "tweet_source": null,
            "rendered_content": "Partido Militar Brasileiro, junte-se a nós: http://lc4.in/BvtD"
        }
    },
    {
        "tweet": {
            "id": 28547191588,
            "creation_date": "2010-10-24 00:25:47",
            "search_type": "User",
            "search_string": "capitao_augusto",
            "like_number": 1,
            "tweet_source": null,
            "rendered_content": "@capitaoassumcao Muito obrigado pela divulgação do PMB em seu site. Unidos somos mais fortes."
        }
    },
    {
        "tweet": {
            "id": 28506588216,
            "creation_date": "2010-10-23 14:48:18",
            "search_type": "User",
            "search_string": "capitao_augusto",
            "like_number": 3,
            "tweet_source": null,
            "rendered_content": "Confira este site: Capitão AUGUSTO -- http://bit.ly/a1wRXN"
        }
    },
    {
        "tweet": {
            "id": 28355869333,
            "creation_date": "2010-10-22 00:26:17",
            "search_type": "User",
            "search_string": "capitao_augusto",
            "like_number": 4,
            "tweet_source": null,
            "rendered_content": "Partido Militar Brasileiro precisa de você: http://www.capitaoaugusto.com.br/adesao.php"
        }
    },
    {
        "tweet": {
            "id": 27956856999,
            "creation_date": "2010-10-20 19:03:03",
            "search_type": "User",
            "search_string": "capitao_augusto",
            "like_number": 1,
            "tweet_source": null,
            "rendered_content": "@priscilaNas O estatuto do Partido Militar Brasileiro esta pronto, confira: www.capitaoaugusto.com.br"
        }
    },
    {
        "tweet": {
            "id": 27956756207,
            "creation_date": "2010-10-20 19:01:37",
            "search_type": "User",
            "search_string": "capitao_augusto",
            "like_number": 1,
            "tweet_source": null,
            "rendered_content": "@celprpaul Paúl o Estatuto do Partido Militar Brasileiro esta pronto, confira: www.capitaoaugusto.com.br"
        }
    },
    {
        "tweet": {
            "id": 27936103531,
            "creation_date": "2010-10-20 14:30:44",
            "search_type": "User",
            "search_string": "capitao_augusto",
            "like_number": 1,
            "tweet_source": null,
            "rendered_content": "@felisbc Obrigado amigo, vamos lutar sempre em prol dos PMs, BMs - PMB"
        }
    },
    {
        "tweet": {
            "id": 27933042141,
            "creation_date": "2010-10-20 13:54:43",
            "search_type": "User",
            "search_string": "capitao_augusto",
            "like_number": 4,
            "tweet_source": null,
            "rendered_content": "Pretendemos estar no DF no próximo mês e gostariamos de um contato pessoal."
        }
    },
    {
        "tweet": {
            "id": 27851959418,
            "creation_date": "2010-10-19 17:09:18",
            "search_type": "User",
            "search_string": "capitao_augusto",
            "like_number": 1,
            "tweet_source": null,
            "rendered_content": "@fernandasbmelo www.capitaoaugusto.com.br"
        }
    },
    {
        "tweet": {
            "id": 27780807035,
            "creation_date": "2010-10-18 23:35:18",
            "search_type": "User",
            "search_string": "capitao_augusto",
            "like_number": 1,
            "tweet_source": null,
            "rendered_content": "@priscilaNas Criação do Partido Militar Brasileiro www.capitaoaugusto.com.br"
        }
    },
    {
        "tweet": {
            "id": 27763145053,
            "creation_date": "2010-10-18 19:35:14",
            "search_type": "User",
            "search_string": "capitao_augusto",
            "like_number": 1,
            "tweet_source": null,
            "rendered_content": "@priscilaNas Criação do Partido Militar do Brasil...Saber mais www.capitaoaugusto.com.br"
        }
    },
    {
        "tweet": {
            "id": 27749083956,
            "creation_date": "2010-10-18 16:16:13",
            "search_type": "User",
            "search_string": "capitao_augusto",
            "like_number": 4,
            "tweet_source": null,
            "rendered_content": "Criação do Partido Militar Brasileiro www.capitaoaugusto.com.br"
        }
    },
    {
        "tweet": {
            "id": 27749032639,
            "creation_date": "2010-10-18 16:15:36",
            "search_type": "User",
            "search_string": "capitao_augusto",
            "like_number": 3,
            "tweet_source": null,
            "rendered_content": "www.capitaoaugusto.com.br"
        }
    },
    {
        "tweet": {
            "id": 27579832899,
            "creation_date": "2010-10-16 22:20:05",
            "search_type": "User",
            "search_string": "capitao_augusto",
            "like_number": 4,
            "tweet_source": null,
            "rendered_content": "Capitão AUGUSTO: CRIAÇÃO DO PARTIDO MILITAR BRASILEIRO blogcapitaoaugusto.blogspot.com/2010/10/criaca…"
        }
    },
    {
        "tweet": {
            "id": 26296983275,
            "creation_date": "2010-10-03 20:10:50",
            "search_type": "User",
            "search_string": "capitao_augusto",
            "like_number": 3,
            "tweet_source": null,
            "rendered_content": "Atentos aos resultados - UNIDOS SOMOS MAIS FORTES...!"
        }
    },
    {
        "tweet": {
            "id": 26209756945,
            "creation_date": "2010-10-02 21:49:40",
            "search_type": "User",
            "search_string": "capitao_augusto",
            "like_number": 4,
            "tweet_source": null,
            "rendered_content": "Amanhã (3) Pelo resgate da dignidade Deputado Federal Capitão AUGUSTO 4020"
        }
    },
    {
        "tweet": {
            "id": 25908822928,
            "creation_date": "2010-09-29 19:00:14",
            "search_type": "User",
            "search_string": "capitao_augusto",
            "like_number": 4,
            "tweet_source": null,
            "rendered_content": "PMs e BMs inatividade aos 25 anos confiram mais em www.capitaoaugusto.com.br"
        }
    },
    {
        "tweet": {
            "id": 25908765847,
            "creation_date": "2010-09-29 18:59:24",
            "search_type": "User",
            "search_string": "capitao_augusto",
            "like_number": 3,
            "tweet_source": null,
            "rendered_content": "3 de outubro Capitão AUGUSTO 4020 para Deputado Federal a hora é agora! www.capitaoaugusto.com.br"
        }
    },
    {
        "tweet": {
            "id": 25625311767,
            "creation_date": "2010-09-26 21:27:14",
            "search_type": "User",
            "search_string": "capitao_augusto",
            "like_number": 2,
            "tweet_source": null,
            "rendered_content": "@Marco_Brasil Policiais Militares de SP conquistam direito a aposentadoria aos 25 anos de serviço: http://lc4.in/eKV"
        }
    },
    {
        "tweet": {
            "id": 25625291788,
            "creation_date": "2010-09-26 21:26:56",
            "search_type": "User",
            "search_string": "capitao_augusto",
            "like_number": 3,
            "tweet_source": null,
            "rendered_content": "Policiais Militares de SP conquistam direito a aposentadoria aos 25 anos de serviço: http://lc4.in/eKV"
        }
    },
    {
        "tweet": {
            "id": 25607848291,
            "creation_date": "2010-09-26 17:14:26",
            "search_type": "User",
            "search_string": "capitao_augusto",
            "like_number": 3,
            "tweet_source": null,
            "rendered_content": "Policiais conquistam direito de aposentadoria aos 25 anos de serviço.: http://ning.it/an0hyT"
        }
    },
    {
        "tweet": {
            "id": 25344649186,
            "creation_date": "2010-09-23 21:41:03",
            "search_type": "User",
            "search_string": "capitao_augusto",
            "like_number": 3,
            "tweet_source": null,
            "rendered_content": "Passagem para a inatividade especial aos 20 ou 25 anos de serviço? http://ning.it/be4w8j"
        }
    },
    {
        "tweet": {
            "id": 25299945442,
            "creation_date": "2010-09-23 11:56:01",
            "search_type": "User",
            "search_string": "capitao_augusto",
            "like_number": 3,
            "tweet_source": null,
            "rendered_content": "Democracia é tema de manifestação http://ning.it/aDhs3u"
        }
    },
    {
        "tweet": {
            "id": 25299934285,
            "creation_date": "2010-09-23 11:55:50",
            "search_type": "User",
            "search_string": "capitao_augusto",
            "like_number": 2,
            "tweet_source": null,
            "rendered_content": "Sem acordo, bancários decidem por greve http://ning.it/aV0gs6"
        }
    },
    {
        "tweet": {
            "id": 25254576328,
            "creation_date": "2010-09-22 23:22:44",
            "search_type": "User",
            "search_string": "capitao_augusto",
            "like_number": 2,
            "tweet_source": null,
            "rendered_content": "Vamos combater o cime: http://lc4.in/696G"
        }
    },
    {
        "tweet": {
            "id": 25146963178,
            "creation_date": "2010-09-21 19:54:59",
            "search_type": "User",
            "search_string": "capitao_augusto",
            "like_number": 0,
            "tweet_source": null,
            "rendered_content": "@priscilaNas @capitaoassumcao IDENTIFICADO OS 812 CANDIDATOS COM CHANCE DE SE ELEGEREM A DEPUTADO FEDERAL NO BRASIL: http://lc4.in/4Hj3"
        }
    },
    {
        "tweet": {
            "id": 25146887911,
            "creation_date": "2010-09-21 19:53:49",
            "search_type": "User",
            "search_string": "capitao_augusto",
            "like_number": 0,
            "tweet_source": null,
            "rendered_content": "@capitaoassumcao IDENTIFICADO OS 812 CANDIDATOS COM CHANCE DE SE ELEGEREM A DEPUTADO FEDERAL NO BRASIL: http://lc4.in/4Hj3"
        }
    },
    {
        "tweet": {
            "id": 25067664201,
            "creation_date": "2010-09-20 23:27:08",
            "search_type": "User",
            "search_string": "capitao_augusto",
            "like_number": 2,
            "tweet_source": null,
            "rendered_content": "BREVIDADE NA REDE: A FAMÍLIA POLICIAL MILITAR PEDE SOCORRO: http://lc4.in/189d"
        }
    },
    {
        "tweet": {
            "id": 24065724409,
            "creation_date": "2010-09-10 02:05:50",
            "search_type": "User",
            "search_string": "capitao_augusto",
            "like_number": 2,
            "tweet_source": null,
            "rendered_content": "Em nosso site vejam as propostas para a cidade de Ourinhos: http://lc4.in/W8WA"
        }
    },
    {
        "tweet": {
            "id": 23060788345,
            "creation_date": "2010-09-05 14:05:32",
            "search_type": "User",
            "search_string": "capitao_augusto",
            "like_number": 2,
            "tweet_source": null,
            "rendered_content": "Brasileiros que trabalham no Canada, EUA, Japão e Africa do Sul e tem seus parentes em São Paulo já declaram seu apoio: http://lc4.in/40E8"
        }
    },
    {
        "tweet": {
            "id": 23060662602,
            "creation_date": "2010-09-05 14:03:45",
            "search_type": "User",
            "search_string": "capitao_augusto",
            "like_number": 2,
            "tweet_source": null,
            "rendered_content": "Nosso site bate record, com média de 2.000 acessos dia, confiram: http://lc4.in/40E8"
        }
    },
    {
        "tweet": {
            "id": 23060568624,
            "creation_date": "2010-09-05 14:02:25",
            "search_type": "User",
            "search_string": "capitao_augusto",
            "like_number": 2,
            "tweet_source": null,
            "rendered_content": "Bom dia e excelente domingo a todos!"
        }
    },
    {
        "tweet": {
            "id": 22085907949,
            "creation_date": "2010-08-25 12:56:15",
            "search_type": "User",
            "search_string": "capitao_augusto",
            "like_number": 2,
            "tweet_source": null,
            "rendered_content": "Bom dia a todos nas graças de nosso Senhor Jesus Cristo."
        }
    },
    {
        "tweet": {
            "id": 22053204182,
            "creation_date": "2010-08-25 02:26:59",
            "search_type": "User",
            "search_string": "capitao_augusto",
            "like_number": 0,
            "tweet_source": null,
            "rendered_content": "@capitaoassumcao Boa noite na paz do Senhor."
        }
    },
    {
        "tweet": {
            "id": 22000179037,
            "creation_date": "2010-08-24 13:25:41",
            "search_type": "User",
            "search_string": "capitao_augusto",
            "like_number": 2,
            "tweet_source": null,
            "rendered_content": "Amigos, vejam vídeo do Cel Miler declarando seu apoio a nossa candidatura: http://lc4.in/T6vE"
        }
    },
    {
        "tweet": {
            "id": 22000131841,
            "creation_date": "2010-08-24 13:24:53",
            "search_type": "User",
            "search_string": "capitao_augusto",
            "like_number": 2,
            "tweet_source": null,
            "rendered_content": "A todos os Policiais e Bombeiros de São Paulo e do Brasil, muito obrigado pelo apoio, unidos somos mais fortes: http://lc4.in/T6vE"
        }
    },
    {
        "tweet": {
            "id": 21680903589,
            "creation_date": "2010-08-20 17:17:02",
            "search_type": "User",
            "search_string": "capitao_augusto",
            "like_number": 2,
            "tweet_source": null,
            "rendered_content": "Do Soldado ao Coronel, agora vai: http://lc4.in/H7N4"
        }
    },
    {
        "tweet": {
            "id": 21583923948,
            "creation_date": "2010-08-19 15:00:32",
            "search_type": "User",
            "search_string": "capitao_augusto",
            "like_number": 2,
            "tweet_source": null,
            "rendered_content": "Representatividade política, o combústivel que move a democracia - Deputado Federal Capitão AUGUSTO 4020 www.capitaoaugusto.com.br"
        }
    },
    {
        "tweet": {
            "id": 21583800819,
            "creation_date": "2010-08-19 14:58:59",
            "search_type": "User",
            "search_string": "capitao_augusto",
            "like_number": 2,
            "tweet_source": null,
            "rendered_content": "Vamos criar uma bancada forte, acerte o alvo = Capitão AUGUSTO 4020 www.capitaoaugusto.com.br"
        }
    },
    {
        "tweet": {
            "id": 21400951987,
            "creation_date": "2010-08-17 12:57:34",
            "search_type": "User",
            "search_string": "capitao_augusto",
            "like_number": 2,
            "tweet_source": null,
            "rendered_content": "PEC300 NA PAUTA DE HOJE (17) VOTAÇÃO EM 2º TURNO, ACOMPANHE TUDO AO VIVO NA COMUNIDADE DOS PMs e BMs DO BRASIL: http://lc4.in/3eq"
        }
    },
    {
        "tweet": {
            "id": 21312397418,
            "creation_date": "2010-08-16 12:53:44",
            "search_type": "User",
            "search_string": "capitao_augusto",
            "like_number": 2,
            "tweet_source": null,
            "rendered_content": "Bom dia!"
        }
    },
    {
        "tweet": {
            "id": 20973988315,
            "creation_date": "2010-08-12 13:14:43",
            "search_type": "User",
            "search_string": "capitao_augusto",
            "like_number": 2,
            "tweet_source": null,
            "rendered_content": "Acusado de matar bombeiro em SP é condenado a 46 anos de prisão: http://lc4.in/Fkjz"
        }
    },
    {
        "tweet": {
            "id": 20700416944,
            "creation_date": "2010-08-09 11:26:40",
            "search_type": "User",
            "search_string": "capitao_augusto",
            "like_number": 2,
            "tweet_source": null,
            "rendered_content": "Bom dia e ótima semana a todos..!"
        }
    },
    {
        "tweet": {
            "id": 20658576910,
            "creation_date": "2010-08-08 22:20:50",
            "search_type": "User",
            "search_string": "capitao_augusto",
            "like_number": 2,
            "tweet_source": null,
            "rendered_content": "Nosso site em apenas 4 mêses atinge 100.000 visitas e o sucesso é seu, confira: http://lc4.in/1kP3"
        }
    },
    {
        "tweet": {
            "id": 20622910492,
            "creation_date": "2010-08-08 11:42:01",
            "search_type": "User",
            "search_string": "capitao_augusto",
            "like_number": 2,
            "tweet_source": null,
            "rendered_content": "Candidatos concentram forças para enfrentar a batalha final na corrida à Presidência: o horário eleitoral gratuito http://ow.ly/2mguD"
        }
    },
    {
        "tweet": {
            "id": 20550806086,
            "creation_date": "2010-08-07 13:18:58",
            "search_type": "User",
            "search_string": "capitao_augusto",
            "like_number": 2,
            "tweet_source": null,
            "rendered_content": "Na nova ISTOÉ: envolver-se em acidente de trânsito e abandonar local não é mais crime. http://ow.ly/2mgnj"
        }
    },
    {
        "tweet": {
            "id": 20550741845,
            "creation_date": "2010-08-07 13:17:49",
            "search_type": "User",
            "search_string": "capitao_augusto",
            "like_number": 2,
            "tweet_source": null,
            "rendered_content": "Processos judiciais revelam como agem PMs corruptos no Rio de Janeiro http://bit.ly/bOjzhV"
        }
    },
    {
        "tweet": {
            "id": 20550699491,
            "creation_date": "2010-08-07 13:17:04",
            "search_type": "User",
            "search_string": "capitao_augusto",
            "like_number": 2,
            "tweet_source": null,
            "rendered_content": "Policial militar é baleado dentro de pizzaria na Praia Grande http://bit.ly/c8amak"
        }
    },
    {
        "tweet": {
            "id": 20550547985,
            "creation_date": "2010-08-07 13:14:37",
            "search_type": "User",
            "search_string": "capitao_augusto",
            "like_number": 2,
            "tweet_source": null,
            "rendered_content": "Christina Lemos: Debate presidencial: o espetáculo pífio da falta de idéias novas http://bit.ly/bPZZwo"
        }
    },
    {
        "tweet": {
            "id": 20550507313,
            "creation_date": "2010-08-07 13:14:00",
            "search_type": "User",
            "search_string": "capitao_augusto",
            "like_number": 2,
            "tweet_source": null,
            "rendered_content": "Tiroteio no Vale do Sinos (RS) deixa um morto e um ferido http://bit.ly/aeHDjI"
        }
    },
    {
        "tweet": {
            "id": 20550486048,
            "creation_date": "2010-08-07 13:13:40",
            "search_type": "User",
            "search_string": "capitao_augusto",
            "like_number": 2,
            "tweet_source": null,
            "rendered_content": "Guarda civil é assassinado em Franco da Rocha http://bit.ly/c2MTE4"
        }
    },
    {
        "tweet": {
            "id": 20461891511,
            "creation_date": "2010-08-06 11:48:08",
            "search_type": "User",
            "search_string": "capitao_augusto",
            "like_number": 2,
            "tweet_source": null,
            "rendered_content": "Bom dia! No oeste do estado de São Paulo 9 graus, tá frio."
        }
    },
    {
        "tweet": {
            "id": 20417926942,
            "creation_date": "2010-08-05 22:50:04",
            "search_type": "User",
            "search_string": "capitao_augusto",
            "like_number": 2,
            "tweet_source": null,
            "rendered_content": "quepasa | Capitão AUGUSTO Augusto Lista de vídeos na internet: www.quepasa.com/video/view.php?id=5923384"
        }
    },
    {
        "tweet": {
            "id": 20382530256,
            "creation_date": "2010-08-05 12:04:03",
            "search_type": "User",
            "search_string": "capitao_augusto",
            "like_number": 2,
            "tweet_source": null,
            "rendered_content": "Câmara pede libertação de iraniana e prorroga CPI sobre violência: http://lc4.in/84Lw"
        }
    },
    {
        "tweet": {
            "id": 20382400364,
            "creation_date": "2010-08-05 12:01:42",
            "search_type": "User",
            "search_string": "capitao_augusto",
            "like_number": 2,
            "tweet_source": null,
            "rendered_content": "Lista de todos os barrados pela ficha limpa: http://lc4.in/vjR5"
        }
    },
    {
        "tweet": {
            "id": 20382293321,
            "creation_date": "2010-08-05 11:59:57",
            "search_type": "User",
            "search_string": "capitao_augusto",
            "like_number": 2,
            "tweet_source": null,
            "rendered_content": "Senado aprova pacote de bondades pré-eleitoral: http://lc4.in/7kVe9"
        }
    },
    {
        "tweet": {
            "id": 20382207869,
            "creation_date": "2010-08-05 11:58:23",
            "search_type": "User",
            "search_string": "capitao_augusto",
            "like_number": 2,
            "tweet_source": null,
            "rendered_content": "Vacarezza inviabiliza votação da PEC300: http://lc4.in/q65N"
        }
    },
    {
        "tweet": {
            "id": 20382025506,
            "creation_date": "2010-08-05 11:55:05",
            "search_type": "User",
            "search_string": "capitao_augusto",
            "like_number": 2,
            "tweet_source": null,
            "rendered_content": "Ficha Limpa passa na primeira prova de fogo. Faltam duas: http://lc4.in/c1Ku"
        }
    },
    {
        "tweet": {
            "id": 20381882565,
            "creation_date": "2010-08-05 11:52:28",
            "search_type": "User",
            "search_string": "capitao_augusto",
            "like_number": 2,
            "tweet_source": null,
            "rendered_content": "Exército terá poder de polícia: http://lc4.in/D5K7"
        }
    },
    {
        "tweet": {
            "id": 20381868721,
            "creation_date": "2010-08-05 11:52:13",
            "search_type": "User",
            "search_string": "capitao_augusto",
            "like_number": 2,
            "tweet_source": null,
            "rendered_content": "Vamos compartilhar as notícias"
        }
    },
    {
        "tweet": {
            "id": 20381829717,
            "creation_date": "2010-08-05 11:51:32",
            "search_type": "User",
            "search_string": "capitao_augusto",
            "like_number": 2,
            "tweet_source": null,
            "rendered_content": "Bom dia..!"
        }
    },
    {
        "tweet": {
            "id": 20340649540,
            "creation_date": "2010-08-04 23:06:37",
            "search_type": "User",
            "search_string": "capitao_augusto",
            "like_number": 0,
            "tweet_source": null,
            "rendered_content": "@capitaoassumcao Postei seu pronunciamento sobre a PEC300 no nosso site, confira: http://lc4.in/LX61"
        }
    },
    {
        "tweet": {
            "id": 20340523657,
            "creation_date": "2010-08-04 23:04:39",
            "search_type": "User",
            "search_string": "capitao_augusto",
            "like_number": 0,
            "tweet_source": null,
            "rendered_content": "@capitaoassumcao Isso ai irmão, a vitória vira em bom tempo - PEC300 Eu acredito..!"
        }
    },
    {
        "tweet": {
            "id": 20338629475,
            "creation_date": "2010-08-04 22:34:58",
            "search_type": "User",
            "search_string": "capitao_augusto",
            "like_number": 2,
            "tweet_source": null,
            "rendered_content": "Mai uma vez a PEC300 fica para depois. Somos guerreiros e vamos continuar lutando, a vitória virá em bom tempo. PEC300 Eu Acredito..!"
        }
    },
    {
        "tweet": {
            "id": 20313012358,
            "creation_date": "2010-08-04 15:37:19",
            "search_type": "User",
            "search_string": "capitao_augusto",
            "like_number": 2,
            "tweet_source": null,
            "rendered_content": "Vaccarezza inclui na pauta desta manhã uma MP inconstitucional e inviabiliza a votação da PEC300: http://ning.it/9Uf4ZV"
        }
    },
    {
        "tweet": {
            "id": 20310978375,
            "creation_date": "2010-08-04 15:07:14",
            "search_type": "User",
            "search_string": "capitao_augusto",
            "like_number": 2,
            "tweet_source": null,
            "rendered_content": "Todos nós estamos cobrando, ajudem vocês também: Disque Câmara 0800 619 619 twitter http://lc4.in/fEbS"
        }
    },
    {
        "tweet": {
            "id": 20310940418,
            "creation_date": "2010-08-04 15:06:42",
            "search_type": "User",
            "search_string": "capitao_augusto",
            "like_number": 2,
            "tweet_source": null,
            "rendered_content": "Estou em campanha no interior de SP e todos nós estamos cobrando, ajudem vocês também: Disque Câmara 0800 619 619 twitter http://lc4.in/fEbS"
        }
    },
    {
        "tweet": {
            "id": 20308952502,
            "creation_date": "2010-08-04 14:37:44",
            "search_type": "User",
            "search_string": "capitao_augusto",
            "like_number": 0,
            "tweet_source": null,
            "rendered_content": "@capitaoassumcao Estou em campanha pelo interior de SP, todos estão ligados hoje Câmara dos Deputados, Estamos juntos. Força e sucesso.!"
        }
    },
    {
        "tweet": {
            "id": 20297536234,
            "creation_date": "2010-08-04 11:31:53",
            "search_type": "User",
            "search_string": "capitao_augusto",
            "like_number": 2,
            "tweet_source": null,
            "rendered_content": "Bom dia! votação da PEC300 acompanhe ao vivo: http://lc4.in/pY0m"
        }
    },
    {
        "tweet": {
            "id": 20258509530,
            "creation_date": "2010-08-03 23:25:33",
            "search_type": "User",
            "search_string": "capitao_augusto",
            "like_number": 2,
            "tweet_source": null,
            "rendered_content": "Em São Paulo estamos todos em QAP/QRV pela PEC300: http://lc4.in/cKaS"
        }
    },
    {
        "tweet": {
            "id": 20257514645,
            "creation_date": "2010-08-03 23:10:24",
            "search_type": "User",
            "search_string": "capitao_augusto",
            "like_number": 2,
            "tweet_source": null,
            "rendered_content": "TV, Rádio, Informações, Política, Alegria e descontração: http://lc4.in/UYGk"
        }
    },
    {
        "tweet": {
            "id": 20256483990,
            "creation_date": "2010-08-03 22:54:10",
            "search_type": "User",
            "search_string": "capitao_augusto",
            "like_number": 2,
            "tweet_source": null,
            "rendered_content": "Votação da PEC300 acompanhe ao vivo: http://lc4.in/78SZ"
        }
    },
    {
        "tweet": {
            "id": 20256457912,
            "creation_date": "2010-08-03 22:53:44",
            "search_type": "User",
            "search_string": "capitao_augusto",
            "like_number": 2,
            "tweet_source": null,
            "rendered_content": "Rádio Polícia, confiram: http://lc4.in/78SZ"
        }
    },
    {
        "tweet": {
            "id": 20251408363,
            "creation_date": "2010-08-03 21:29:25",
            "search_type": "User",
            "search_string": "capitao_augusto",
            "like_number": 2,
            "tweet_source": null,
            "rendered_content": "Votação 2º turno da PEC300 acompanhe ao vivo: http://lc4.in/1D6t"
        }
    },
    {
        "tweet": {
            "id": 20228032988,
            "creation_date": "2010-08-03 15:02:52",
            "search_type": "User",
            "search_string": "capitao_augusto",
            "like_number": 2,
            "tweet_source": null,
            "rendered_content": "Pessam aos Parlamentares que a PEC300 seja pautada e aprovada: http://bit.ly/9bwXMf"
        }
    },
    {
        "tweet": {
            "id": 20216688305,
            "creation_date": "2010-08-03 12:09:46",
            "search_type": "User",
            "search_string": "capitao_augusto",
            "like_number": 2,
            "tweet_source": null,
            "rendered_content": "Pelo menos três carros e um ônibus foram incendiados na Grande São Paulo na madrugada desta terça-feira (3)"
        }
    },
    {
        "tweet": {
            "id": 20215443872,
            "creation_date": "2010-08-03 11:46:57",
            "search_type": "User",
            "search_string": "capitao_augusto",
            "like_number": 2,
            "tweet_source": null,
            "rendered_content": "Rádio Polícia no twitter: http://twitter.com/radiopolicia"
        }
    },
    {
        "tweet": {
            "id": 20215403911,
            "creation_date": "2010-08-03 11:46:17",
            "search_type": "User",
            "search_string": "capitao_augusto",
            "like_number": 2,
            "tweet_source": null,
            "rendered_content": "http://twitter.com/radiopolicia"
        }
    },
    {
        "tweet": {
            "id": 20215338521,
            "creation_date": "2010-08-03 11:45:01",
            "search_type": "User",
            "search_string": "capitao_augusto",
            "like_number": 2,
            "tweet_source": null,
            "rendered_content": "Ajudem a divulgar esta idéia: http://www.radiopolicia.com.br/"
        }
    },
    {
        "tweet": {
            "id": 20160640211,
            "creation_date": "2010-08-02 19:02:07",
            "search_type": "User",
            "search_string": "capitao_augusto",
            "like_number": 2,
            "tweet_source": null,
            "rendered_content": "Lista dos Parlamentares que possuem twitter, fica mais fácil enviar seu recado: http://lc4.in/7FZz"
        }
    },
    {
        "tweet": {
            "id": 20160348070,
            "creation_date": "2010-08-02 18:57:19",
            "search_type": "User",
            "search_string": "capitao_augusto",
            "like_number": 2,
            "tweet_source": null,
            "rendered_content": "PEC300 pode ser votada em 2º turno esta semana: http://lc4.in/Pxo7"
        }
    },
    {
        "tweet": {
            "id": 20159136936,
            "creation_date": "2010-08-02 18:36:18",
            "search_type": "User",
            "search_string": "capitao_augusto",
            "like_number": 0,
            "tweet_source": null,
            "rendered_content": "@FernandoCapez Já descobri: http://lc4.in/yl8"
        }
    },
    {
        "tweet": {
            "id": 20158764947,
            "creation_date": "2010-08-02 18:29:56",
            "search_type": "User",
            "search_string": "capitao_augusto",
            "like_number": 0,
            "tweet_source": null,
            "rendered_content": "@FernandoCapez Ensina como se faz - rs."
        }
    },
    {
        "tweet": {
            "id": 20139528172,
            "creation_date": "2010-08-02 13:33:23",
            "search_type": "User",
            "search_string": "capitao_augusto",
            "like_number": 2,
            "tweet_source": null,
            "rendered_content": "Homens vestidos de policiais roubam R$ 700 mil de banco em SP: http://lc4.in/8Kbh"
        }
    },
    {
        "tweet": {
            "id": 20133686514,
            "creation_date": "2010-08-02 11:56:26",
            "search_type": "User",
            "search_string": "capitao_augusto",
            "like_number": 2,
            "tweet_source": null,
            "rendered_content": "Bom dia e ótima semana a todos: www.capitaoagusto.com.br"
        }
    },
    {
        "tweet": {
            "id": 20104370449,
            "creation_date": "2010-08-02 01:50:59",
            "search_type": "User",
            "search_string": "capitao_augusto",
            "like_number": 2,
            "tweet_source": null,
            "rendered_content": "Goldman, Governador de São Paulo, em vídeo fala sobre os atentados no estado à ROTA: http://lc4.in/1JF0"
        }
    },
    {
        "tweet": {
            "id": 20085676413,
            "creation_date": "2010-08-01 20:26:41",
            "search_type": "User",
            "search_string": "capitao_augusto",
            "like_number": 2,
            "tweet_source": null,
            "rendered_content": "POLÍCIA MILITAR PEC300 PODE SER VOTADA ESTA SEMANA: http://lc4.in/SRa"
        }
    },
    {
        "tweet": {
            "id": 20085299572,
            "creation_date": "2010-08-01 20:19:10",
            "search_type": "User",
            "search_string": "capitao_augusto",
            "like_number": 2,
            "tweet_source": null,
            "rendered_content": "PEC300 deve ser votada nesta semana: http://lc4.in/Z79p"
        }
    },
    {
        "tweet": {
            "id": 20071510047,
            "creation_date": "2010-08-01 16:03:24",
            "search_type": "User",
            "search_string": "capitao_augusto",
            "like_number": 2,
            "tweet_source": null,
            "rendered_content": "Presídios vão usar até enfermaria para assegurar voto de detentos: http://lc4.in/46cL"
        }
    },
    {
        "tweet": {
            "id": 20063440976,
            "creation_date": "2010-08-01 13:53:09",
            "search_type": "User",
            "search_string": "capitao_augusto",
            "like_number": 2,
            "tweet_source": null,
            "rendered_content": "No sábado o Cmt da ROTA sofre atentado e na madrugada de domingo o atentado e contra o quartel: http://lc4.in/hyZ3"
        }
    },
    {
        "tweet": {
            "id": 20062819907,
            "creation_date": "2010-08-01 13:42:39",
            "search_type": "User",
            "search_string": "capitao_augusto",
            "like_number": 2,
            "tweet_source": null,
            "rendered_content": "Quartel da ROTA sofre atentado na madrugada de domingo em 01 de agosto de 2010: http://lc4.in/0R8h"
        }
    },
    {
        "tweet": {
            "id": 20061374458,
            "creation_date": "2010-08-01 13:16:28",
            "search_type": "User",
            "search_string": "capitao_augusto",
            "like_number": 2,
            "tweet_source": null,
            "rendered_content": "Bom domingo a todos"
        }
    },
    {
        "tweet": {
            "id": 20031717563,
            "creation_date": "2010-08-01 01:29:52",
            "search_type": "User",
            "search_string": "capitao_augusto",
            "like_number": 2,
            "tweet_source": null,
            "rendered_content": "VÍDEO DO ATENTADO CONTRA O CMT DA ROTA TCEL TELHADA: http://ning.it/9vAbNI"
        }
    },
    {
        "tweet": {
            "id": 19988534824,
            "creation_date": "2010-07-31 12:36:13",
            "search_type": "User",
            "search_string": "capitao_augusto",
            "like_number": 2,
            "tweet_source": null,
            "rendered_content": "A lista completa dos que desistiram para não enfrentar a ficha limpa. http://ning.it/boejHK"
        }
    },
    {
        "tweet": {
            "id": 19944132969,
            "creation_date": "2010-07-30 22:29:27",
            "search_type": "User",
            "search_string": "capitao_augusto",
            "like_number": 2,
            "tweet_source": null,
            "rendered_content": "\"Governador da Bahia diz que policial militar é semelhante a burro\" no PolicialBR.: http://ning.it/c0OneQ"
        }
    },
    {
        "tweet": {
            "id": 19944054970,
            "creation_date": "2010-07-30 22:28:05",
            "search_type": "User",
            "search_string": "capitao_augusto",
            "like_number": 2,
            "tweet_source": null,
            "rendered_content": "pec300 Polícia Militar\"Alckmin (PSDB) disse que os policiais militares devem trabalhar 08 hora PolicialBR: http://ning.it/9dx1a0"
        }
    },
    {
        "tweet": {
            "id": 19918076527,
            "creation_date": "2010-07-30 15:32:44",
            "search_type": "User",
            "search_string": "capitao_augusto",
            "like_number": 0,
            "tweet_source": null,
            "rendered_content": "@flaviopgodoi Caro Maj Flávio, muito obrigado, também estou te seguindo no twitter, conte sempre comigo, abraço e sucesso!"
        }
    },
    {
        "tweet": {
            "id": 19908507681,
            "creation_date": "2010-07-30 13:11:32",
            "search_type": "User",
            "search_string": "capitao_augusto",
            "like_number": 0,
            "tweet_source": null,
            "rendered_content": "@Marco_Brasil Bom dia amigo, abraço!"
        }
    },
    {
        "tweet": {
            "id": 19905212966,
            "creation_date": "2010-07-30 12:14:17",
            "search_type": "User",
            "search_string": "capitao_augusto",
            "like_number": 2,
            "tweet_source": null,
            "rendered_content": "\"não precisa correr tanto o que tiver de ser seu as mãos lhe a de ir\" Machado de Assis"
        }
    },
    {
        "tweet": {
            "id": 19905163011,
            "creation_date": "2010-07-30 12:13:23",
            "search_type": "User",
            "search_string": "capitao_augusto",
            "like_number": 2,
            "tweet_source": null,
            "rendered_content": "Bom dia!"
        }
    },
    {
        "tweet": {
            "id": 19874713718,
            "creation_date": "2010-07-30 02:18:16",
            "search_type": "User",
            "search_string": "capitao_augusto",
            "like_number": 2,
            "tweet_source": null,
            "rendered_content": "Texto da PEC300 aprovado em 1º turno http://ning.it/9kjr0X"
        }
    },
    {
        "tweet": {
            "id": 19864690792,
            "creation_date": "2010-07-29 23:44:03",
            "search_type": "User",
            "search_string": "capitao_augusto",
            "like_number": 2,
            "tweet_source": null,
            "rendered_content": "Governador da Bahia diz que PM é semelhante a burro de carroça, tem que trabalhar na báse da chicotada http://ning.it/c0OneQ"
        }
    },
    {
        "tweet": {
            "id": 19863355614,
            "creation_date": "2010-07-29 23:22:56",
            "search_type": "User",
            "search_string": "capitao_augusto",
            "like_number": 2,
            "tweet_source": null,
            "rendered_content": "Alckmin: PMs devem trabalhar 8 horas dentro das 36 horas de folga que têm, de forma a elevar o efetivo na rua. http://ning.it/9VxE0Y"
        }
    },
    {
        "tweet": {
            "id": 19863100388,
            "creation_date": "2010-07-29 23:18:58",
            "search_type": "User",
            "search_string": "capitao_augusto",
            "like_number": 2,
            "tweet_source": null,
            "rendered_content": "Alckmin disse que os PMs devem trabalhar 8 horas dentro das 36 de folga que têm, de forma a elevar o efetivo na rua: http://lc4.in/m7Qp"
        }
    },
    {
        "tweet": {
            "id": 19859826856,
            "creation_date": "2010-07-29 22:27:28",
            "search_type": "User",
            "search_string": "capitao_augusto",
            "like_number": 2,
            "tweet_source": null,
            "rendered_content": "Um guia para votar em ficha limpa http://ning.it/9IJzLH"
        }
    },
    {
        "tweet": {
            "id": 19859694108,
            "creation_date": "2010-07-29 22:25:15",
            "search_type": "User",
            "search_string": "capitao_augusto",
            "like_number": 2,
            "tweet_source": null,
            "rendered_content": "Um guia para votar em ficha limpa: http://lc4.in/a2A9"
        }
    },
    {
        "tweet": {
            "id": 19827438873,
            "creation_date": "2010-07-29 13:54:30",
            "search_type": "User",
            "search_string": "capitao_augusto",
            "like_number": 2,
            "tweet_source": null,
            "rendered_content": "A Polícia Militar é uma das mais antigas e maiores instituições do país... http://goo.gl/b/uwqU"
        }
    },
    {
        "tweet": {
            "id": 19819998685,
            "creation_date": "2010-07-29 11:56:42",
            "search_type": "User",
            "search_string": "capitao_augusto",
            "like_number": 0,
            "tweet_source": null,
            "rendered_content": "@paulo_skaf Sucesso!"
        }
    },
    {
        "tweet": {
            "id": 19775242704,
            "creation_date": "2010-07-28 22:30:36",
            "search_type": "User",
            "search_string": "capitao_augusto",
            "like_number": 1,
            "tweet_source": null,
            "rendered_content": "Mais ideias e menos marketing na televisão: http://congressoemfoco.uol.com.br/noticia.asp?cod_publicacao=33805&cod_canal=1"
        }
    },
    {
        "tweet": {
            "id": 19762878671,
            "creation_date": "2010-07-28 18:58:58",
            "search_type": "User",
            "search_string": "capitao_augusto",
            "like_number": 0,
            "tweet_source": null,
            "rendered_content": "@FernandoCapez Muito obrigado, você é nosso amigo, acesse e confira www.policialbr.com"
        }
    },
    {
        "tweet": {
            "id": 19762099856,
            "creation_date": "2010-07-28 18:45:30",
            "search_type": "User",
            "search_string": "capitao_augusto",
            "like_number": 0,
            "tweet_source": null,
            "rendered_content": "@FernandoCapez Sucesso!"
        }
    },
    {
        "tweet": {
            "id": 19761505644,
            "creation_date": "2010-07-28 18:35:29",
            "search_type": "User",
            "search_string": "capitao_augusto",
            "like_number": 0,
            "tweet_source": null,
            "rendered_content": "@capitaoassumcao Parabéns Assumção pelo trabalho que vem realizando em prol da PEC300 e também aos demais que estão empenhados."
        }
    },
    {
        "tweet": {
            "id": 19761284710,
            "creation_date": "2010-07-28 18:31:47",
            "search_type": "User",
            "search_string": "capitao_augusto",
            "like_number": 0,
            "tweet_source": null,
            "rendered_content": "@capitaoassumcao Sim, pressão democrática e de direito!"
        }
    },
    {
        "tweet": {
            "id": 19760871482,
            "creation_date": "2010-07-28 18:24:59",
            "search_type": "User",
            "search_string": "capitao_augusto",
            "like_number": 0,
            "tweet_source": null,
            "rendered_content": "@capitaoassumcao Sem dúvida alguma e a começar com salários dignos aos policiais e bombeiros porque o maior patrimônio é o ser humano"
        }
    },
    {
        "tweet": {
            "id": 19760227374,
            "creation_date": "2010-07-28 18:14:23",
            "search_type": "User",
            "search_string": "capitao_augusto",
            "like_number": 0,
            "tweet_source": null,
            "rendered_content": "@capitaoassumcao Ontem (28) foram presas algumas \"mulas sem alça\" na cidade de Salto Grande/SP, região de ourinhos."
        }
    },
    {
        "tweet": {
            "id": 19759078984,
            "creation_date": "2010-07-28 17:55:50",
            "search_type": "User",
            "search_string": "capitao_augusto",
            "like_number": 0,
            "tweet_source": null,
            "rendered_content": "@paulo_skaf Vamos em frente, sucesso!"
        }
    },
    {
        "tweet": {
            "id": 19754532264,
            "creation_date": "2010-07-28 16:45:48",
            "search_type": "User",
            "search_string": "capitao_augusto",
            "like_number": 1,
            "tweet_source": null,
            "rendered_content": "corrigindo: preservar o adolescente de ser vítima de um MAL maior. Os orgãos públicos poderiam distribuir, grátuitamente, este software"
        }
    },
    {
        "tweet": {
            "id": 19754086783,
            "creation_date": "2010-07-28 16:39:10",
            "search_type": "User",
            "search_string": "capitao_augusto",
            "like_number": 0,
            "tweet_source": null,
            "rendered_content": "@paulo_skaf Estou te seguindo no twitter"
        }
    },
    {
        "tweet": {
            "id": 19753172436,
            "creation_date": "2010-07-28 16:25:57",
            "search_type": "User",
            "search_string": "capitao_augusto",
            "like_number": 0,
            "tweet_source": null,
            "rendered_content": "@capitaoassumcao da mesma forma que o poder público distribui outros meios de proteção ao ser humano"
        }
    },
    {
        "tweet": {
            "id": 19752974662,
            "creation_date": "2010-07-28 16:23:06",
            "search_type": "User",
            "search_string": "capitao_augusto",
            "like_number": 0,
            "tweet_source": null,
            "rendered_content": "@capitaoassumcao preservar o adolescente de ser vítima de um mau maior. Os orgãos públicos poderiam distribuir, grátuitamente, este software"
        }
    },
    {
        "tweet": {
            "id": 19752843837,
            "creation_date": "2010-07-28 16:21:15",
            "search_type": "User",
            "search_string": "capitao_augusto",
            "like_number": 0,
            "tweet_source": null,
            "rendered_content": "@capitaoassumcao É uma \"privação de privacidade\", porém, necessária para coibir o uso inadequado da rede e..."
        }
    },
    {
        "tweet": {
            "id": 19752394893,
            "creation_date": "2010-07-28 16:14:42",
            "search_type": "User",
            "search_string": "capitao_augusto",
            "like_number": 0,
            "tweet_source": null,
            "rendered_content": "@capitaoassumcao Já existem softwares que monitoram o computador e exibem, aos pais ou responsáveis, tudo o que \"foi feito\" (log)..."
        }
    },
    {
        "tweet": {
            "id": 19747187233,
            "creation_date": "2010-07-28 15:01:54",
            "search_type": "User",
            "search_string": "capitao_augusto",
            "like_number": 1,
            "tweet_source": null,
            "rendered_content": "Educação digital este é o caminho para relações sociais saudáveis e seguras por meio do uso adequado das tecnologias."
        }
    },
    {
        "tweet": {
            "id": 19746856417,
            "creation_date": "2010-07-28 14:57:40",
            "search_type": "User",
            "search_string": "capitao_augusto",
            "like_number": 0,
            "tweet_source": null,
            "rendered_content": "@capitaoassumcao Concordo com a divulgação porque os pais, na maioria das vezes, não sabe o que os filhos fazem na internet."
        }
    },
    {
        "tweet": {
            "id": 19746378116,
            "creation_date": "2010-07-28 14:51:08",
            "search_type": "User",
            "search_string": "capitao_augusto",
            "like_number": 0,
            "tweet_source": null,
            "rendered_content": "@capitaoassumcao Tema complicado (sexting) só com um trabalho educacional e de conscientização será possível combater tal ato"
        }
    },
    {
        "tweet": {
            "id": 19745770107,
            "creation_date": "2010-07-28 14:42:46",
            "search_type": "User",
            "search_string": "capitao_augusto",
            "like_number": 0,
            "tweet_source": null,
            "rendered_content": "@celprpaul Boa notícia Cel Paul campnha PM vota em PM"
        }
    },
    {
        "tweet": {
            "id": 19745227628,
            "creation_date": "2010-07-28 14:35:21",
            "search_type": "User",
            "search_string": "capitao_augusto",
            "like_number": 1,
            "tweet_source": null,
            "rendered_content": "Estamos em São Paulo, gravando para TV"
        }
    },
    {
        "tweet": {
            "id": 19743961872,
            "creation_date": "2010-07-28 14:18:12",
            "search_type": "User",
            "search_string": "capitao_augusto",
            "like_number": 1,
            "tweet_source": null,
            "rendered_content": "Acessem www.policialbr.com para conhecer os candidatos militares a deputado federal dos estados"
        }
    },
    {
        "tweet": {
            "id": 19743444021,
            "creation_date": "2010-07-28 14:11:03",
            "search_type": "User",
            "search_string": "capitao_augusto",
            "like_number": 1,
            "tweet_source": null,
            "rendered_content": "Campanha PM vota em PM a importância de uma bancada militar, unidos somos mais fortes Dep Federal Capitão AUGUSTO 4020 - é isso ai Cel Paul"
        }
    },
    {
        "tweet": {
            "id": 19609027099,
            "creation_date": "2010-07-26 23:01:56",
            "search_type": "User",
            "search_string": "capitao_augusto",
            "like_number": 1,
            "tweet_source": null,
            "rendered_content": "CAMPANHA \"UM DEPUTADO FEDERAL MILITAR POR ESTADO\" AJUDE A DIVULGAR ESTA IDÉIA: http://policialbr.com/page/candidados-militares"
        }
    },
    {
        "tweet": {
            "id": 19529133429,
            "creation_date": "2010-07-25 23:33:24",
            "search_type": "User",
            "search_string": "capitao_augusto",
            "like_number": 1,
            "tweet_source": null,
            "rendered_content": "Capitão AUGUSTO 4020 já esta entre os Deputados Federais mais votados de São Paulo: www.capitaoaugusto.com.br http://ning.it/d1YBj5"
        }
    },
    {
        "tweet": {
            "id": 19520459451,
            "creation_date": "2010-07-25 20:49:43",
            "search_type": "User",
            "search_string": "capitao_augusto",
            "like_number": 1,
            "tweet_source": null,
            "rendered_content": "Cabo Bentinho precursor do policiamento comunitário. http://ning.it/ch1MM4"
        }
    },
    {
        "tweet": {
            "id": 19516717203,
            "creation_date": "2010-07-25 19:34:19",
            "search_type": "User",
            "search_string": "capitao_augusto",
            "like_number": 1,
            "tweet_source": null,
            "rendered_content": "PEC300 e o lobo mau 446 http://ning.it/dexOaF"
        }
    },
    {
        "tweet": {
            "id": 19380555581,
            "creation_date": "2010-07-24 00:33:46",
            "search_type": "User",
            "search_string": "capitao_augusto",
            "like_number": 1,
            "tweet_source": null,
            "rendered_content": "Cancelado debate on-line com presidenciáveis www.policialbr.com http://ning.it/buxHxO"
        }
    },
    {
        "tweet": {
            "id": 19369631812,
            "creation_date": "2010-07-23 21:23:34",
            "search_type": "User",
            "search_string": "capitao_augusto",
            "like_number": 1,
            "tweet_source": null,
            "rendered_content": "TSE define regras para uso da internet nas eleições 2010 www.policialbr.com http://ning.it/bk9bSk"
        }
    },
    {
        "tweet": {
            "id": 19041976444,
            "creation_date": "2010-07-21 02:25:30",
            "search_type": "User",
            "search_string": "capitao_augusto",
            "like_number": 1,
            "tweet_source": null,
            "rendered_content": "Candidatos Fardados http://ning.it/c5V8Dm"
        }
    },
    {
        "tweet": {
            "id": 18910420100,
            "creation_date": "2010-07-19 11:59:14",
            "search_type": "User",
            "search_string": "capitao_augusto",
            "like_number": 1,
            "tweet_source": null,
            "rendered_content": "\"Não precisa correr tanto, o que tiver de ser seu as mãos lhe a de ir\" - Machado de Assis"
        }
    },
    {
        "tweet": {
            "id": 18867128140,
            "creation_date": "2010-07-18 22:03:05",
            "search_type": "User",
            "search_string": "capitao_augusto",
            "like_number": 1,
            "tweet_source": null,
            "rendered_content": "Grupo Bancada Militar Forte em Policiais e Bombeiros do Brasil http://ning.it/byQolh"
        }
    },
    {
        "tweet": {
            "id": 18866452544,
            "creation_date": "2010-07-18 21:49:24",
            "search_type": "User",
            "search_string": "capitao_augusto",
            "like_number": 0,
            "tweet_source": null,
            "rendered_content": "@celprpaul Sou candidato a deputado federal por São Paulo Capitão AUGUSTO 4020 vamos unir forças em prol de nossa categoria..!"
        }
    },
    {
        "tweet": {
            "id": 18796473460,
            "creation_date": "2010-07-17 22:53:10",
            "search_type": "User",
            "search_string": "capitao_augusto",
            "like_number": 1,
            "tweet_source": null,
            "rendered_content": "PEC300 Votação em 2º turno fica para agosto, veja vídeo em nosso site: www.capitaoaugusto.com.br"
        }
    },
    {
        "tweet": {
            "id": 18723053108,
            "creation_date": "2010-07-16 23:20:24",
            "search_type": "User",
            "search_string": "capitao_augusto",
            "like_number": 1,
            "tweet_source": null,
            "rendered_content": "Venha participar do grupo sobre colecionismo de antiguidades policiais e militares em PolicialBR.: http://ning.it/ah3O1R"
        }
    },
    {
        "tweet": {
            "id": 18720730689,
            "creation_date": "2010-07-16 22:39:05",
            "search_type": "User",
            "search_string": "capitao_augusto",
            "like_number": 1,
            "tweet_source": null,
            "rendered_content": "Porque o Capitão AUGUSTO é o candidato mais viável?\n\nLeia mais: http://www.policialbr.com/#ixzz0tt6T0i3s"
        }
    },
    {
        "tweet": {
            "id": 18720705260,
            "creation_date": "2010-07-16 22:38:37",
            "search_type": "User",
            "search_string": "capitao_augusto",
            "like_number": 1,
            "tweet_source": null,
            "rendered_content": "Quem não gosta de política e não elege seus representantes fica subordinado a vontade daqueles que gostam e elegem os seus."
        }
    },
    {
        "tweet": {
            "id": 18720676580,
            "creation_date": "2010-07-16 22:38:06",
            "search_type": "User",
            "search_string": "capitao_augusto",
            "like_number": 1,
            "tweet_source": null,
            "rendered_content": "10 - Policial vota em Policial pela Polícia e pelo Povo:\n\nRead more: http://www.policialbr.com/#ixzz0tt6G4xn4"
        }
    },
    {
        "tweet": {
            "id": 18720663535,
            "creation_date": "2010-07-16 22:37:52",
            "search_type": "User",
            "search_string": "capitao_augusto",
            "like_number": 1,
            "tweet_source": null,
            "rendered_content": "9 - já visitou mais de 400 municípios somente este ano:\n*** pelas fotos no site e orkut é possivel ver as cidades visitadas,"
        }
    },
    {
        "tweet": {
            "id": 18720643379,
            "creation_date": "2010-07-16 22:37:30",
            "search_type": "User",
            "search_string": "capitao_augusto",
            "like_number": 1,
            "tweet_source": null,
            "rendered_content": "8 - Escolha do Partido PSB: oportunidade de escolher um partido que realmente possibilite se eleger com o menor número de votos"
        }
    },
    {
        "tweet": {
            "id": 18720599321,
            "creation_date": "2010-07-16 22:36:42",
            "search_type": "User",
            "search_string": "capitao_augusto",
            "like_number": 1,
            "tweet_source": null,
            "rendered_content": "7 - É da ATIVA:\n*** diferente de outros que esperam garantir todos seus direitos para sair candidato"
        }
    },
    {
        "tweet": {
            "id": 18720577262,
            "creation_date": "2010-07-16 22:36:18",
            "search_type": "User",
            "search_string": "capitao_augusto",
            "like_number": 1,
            "tweet_source": null,
            "rendered_content": "6 - Já trabalhou na Capital e Interior sabendo com propriedade suas diferenças e dificuldades particulares"
        }
    },
    {
        "tweet": {
            "id": 18720531646,
            "creation_date": "2010-07-16 22:35:30",
            "search_type": "User",
            "search_string": "capitao_augusto",
            "like_number": 1,
            "tweet_source": null,
            "rendered_content": "5 - Já trabalhou no Corpo de Bombeiros, Policiamento Rodoviário e Policiamento Urbano:"
        }
    },
    {
        "tweet": {
            "id": 18720498839,
            "creation_date": "2010-07-16 22:34:56",
            "search_type": "User",
            "search_string": "capitao_augusto",
            "like_number": 1,
            "tweet_source": null,
            "rendered_content": "4 É o principal candidato da região de Ourinhos que tem 200 mil eleitores:"
        }
    },
    {
        "tweet": {
            "id": 18720345998,
            "creation_date": "2010-07-16 22:32:11",
            "search_type": "User",
            "search_string": "capitao_augusto",
            "like_number": 1,
            "tweet_source": null,
            "rendered_content": "2 Ficou como Suplente em 2002 e Primeiro Suplente em 2006:\nesta é sua terceira candidatura, por duas vezes não se elegeu por muito pouco"
        }
    },
    {
        "tweet": {
            "id": 18720309925,
            "creation_date": "2010-07-16 22:31:32",
            "search_type": "User",
            "search_string": "capitao_augusto",
            "like_number": 1,
            "tweet_source": null,
            "rendered_content": "1 Foi o candidato mais votado da Polícia Militar\nem 2006 Capitão AUGUSTO obteve 41.133 votos, o segundo colocado não chegou a 9 mil votos;"
        }
    },
    {
        "tweet": {
            "id": 18720251685,
            "creation_date": "2010-07-16 22:30:29",
            "search_type": "User",
            "search_string": "capitao_augusto",
            "like_number": 1,
            "tweet_source": null,
            "rendered_content": "Dez motivos para votar no Capitão AUGUSTO 4020 para deputado federal"
        }
    },
    {
        "tweet": {
            "id": 18711681473,
            "creation_date": "2010-07-16 19:52:17",
            "search_type": "User",
            "search_string": "capitao_augusto",
            "like_number": 1,
            "tweet_source": null,
            "rendered_content": "No nosso site só falta você: www.capitaoaugusto.com.br"
        }
    },
    {
        "tweet": {
            "id": 18689010045,
            "creation_date": "2010-07-16 14:18:54",
            "search_type": "User",
            "search_string": "capitao_augusto",
            "like_number": 1,
            "tweet_source": null,
            "rendered_content": "PEC300/Polícia Militar \"1º debate das eleições 2010 pela internet dia 26 de julho portais IG, MSN, Terra e Yahoo!: http://ning.it/9nmcUs"
        }
    },
    {
        "tweet": {
            "id": 18688693646,
            "creation_date": "2010-07-16 14:14:50",
            "search_type": "User",
            "search_string": "capitao_augusto",
            "like_number": 1,
            "tweet_source": null,
            "rendered_content": "Brasil terá o 1º debate das eleições 2010 pela internet nos portais IG, MSN, Terra e Yahoo! no dia 26 de julho http://ning.it/9nmcUs"
        }
    },
    {
        "tweet": {
            "id": 18683828803,
            "creation_date": "2010-07-16 13:04:43",
            "search_type": "User",
            "search_string": "capitao_augusto",
            "like_number": 0,
            "tweet_source": null,
            "rendered_content": "@marco_brasil Nosso CD tá tocando lá...!"
        }
    },
    {
        "tweet": {
            "id": 18683774662,
            "creation_date": "2010-07-16 13:03:56",
            "search_type": "User",
            "search_string": "capitao_augusto",
            "like_number": 0,
            "tweet_source": null,
            "rendered_content": "@marco_brasil Amigo, venha participar da Comunidade dos Policiais e Bombeiros do Brasil: www.policialbr.com"
        }
    },
    {
        "tweet": {
            "id": 18683652711,
            "creation_date": "2010-07-16 13:02:08",
            "search_type": "User",
            "search_string": "capitao_augusto",
            "like_number": 0,
            "tweet_source": null,
            "rendered_content": "@Marco_Brasil Vai com Deus meu amigo e sucesso!"
        }
    },
    {
        "tweet": {
            "id": 18683265873,
            "creation_date": "2010-07-16 12:56:33",
            "search_type": "User",
            "search_string": "capitao_augusto",
            "like_number": 1,
            "tweet_source": null,
            "rendered_content": "Conferindo \"Peça de fardamento belíssima: Os Laços Hungaros\" no Policiais e Bombeiros do Brasil.: http://ning.it/bPMiA1"
        }
    },
    {
        "tweet": {
            "id": 18683240535,
            "creation_date": "2010-07-16 12:56:08",
            "search_type": "User",
            "search_string": "capitao_augusto",
            "like_number": 1,
            "tweet_source": null,
            "rendered_content": "Conferindo \"Brevês de cursos da PMESP\" no Policiais e Bombeiros do Brasil.: http://ning.it/cx3bif"
        }
    },
    {
        "tweet": {
            "id": 18683220751,
            "creation_date": "2010-07-16 12:55:49",
            "search_type": "User",
            "search_string": "capitao_augusto",
            "like_number": 1,
            "tweet_source": null,
            "rendered_content": "Conferindo \"Espada misteriosa\" no Policiais e Bombeiros do Brasil.: http://ning.it/cHazSt"
        }
    },
    {
        "tweet": {
            "id": 18683159206,
            "creation_date": "2010-07-16 12:54:51",
            "search_type": "User",
            "search_string": "capitao_augusto",
            "like_number": 1,
            "tweet_source": null,
            "rendered_content": "Conferindo \"Medalha de combatente da Guerra do Paraguai.\" no Policiais e Bombeiros do Brasil.: http://ning.it/crger8"
        }
    },
    {
        "tweet": {
            "id": 18682632017,
            "creation_date": "2010-07-16 12:46:22",
            "search_type": "User",
            "search_string": "capitao_augusto",
            "like_number": 1,
            "tweet_source": null,
            "rendered_content": "Conferindo \"Peça de fardamento belíssima: Os Laços Hungaros\" no Policiais e Bombeiros do Brasil.: http://ning.it/avx50L"
        }
    },
    {
        "tweet": {
            "id": 18682602859,
            "creation_date": "2010-07-16 12:45:55",
            "search_type": "User",
            "search_string": "capitao_augusto",
            "like_number": 1,
            "tweet_source": null,
            "rendered_content": "Conferindo \"Brevês de cursos da PMESP\" no Policiais e Bombeiros do Brasil.: http://ning.it/aCsj0n"
        }
    },
    {
        "tweet": {
            "id": 18682510177,
            "creation_date": "2010-07-16 12:44:25",
            "search_type": "User",
            "search_string": "capitao_augusto",
            "like_number": 1,
            "tweet_source": null,
            "rendered_content": "Conferindo \"Espada misteriosa\" no Policiais e Bombeiros do Brasil.: http://ning.it/cxsJAa"
        }
    },
    {
        "tweet": {
            "id": 18682493105,
            "creation_date": "2010-07-16 12:44:09",
            "search_type": "User",
            "search_string": "capitao_augusto",
            "like_number": 1,
            "tweet_source": null,
            "rendered_content": "Conferindo \"Medalha de combatente da Guerra do Paraguai.\" no Policiais e Bombeiros do Brasil.: http://ning.it/ah3O1R"
        }
    },
    {
        "tweet": {
            "id": 18682326341,
            "creation_date": "2010-07-16 12:41:28",
            "search_type": "User",
            "search_string": "capitao_augusto",
            "like_number": 1,
            "tweet_source": null,
            "rendered_content": "O Maj Galdino em PolicialBR criou o grupo COLECIONISMO DE ANTIGUIDADES POLICIAIS E MILITARES www.policialbr.com"
        }
    },
    {
        "tweet": {
            "id": 18680828328,
            "creation_date": "2010-07-16 12:16:35",
            "search_type": "User",
            "search_string": "capitao_augusto",
            "like_number": 1,
            "tweet_source": null,
            "rendered_content": "Morreu o catarinense Gilberto Pedro Hoffman Nahas, aos 81 anos, de câncer. http://naufrago-da-utopia.blogspot.com"
        }
    },
    {
        "tweet": {
            "id": 18680772779,
            "creation_date": "2010-07-16 12:15:39",
            "search_type": "User",
            "search_string": "capitao_augusto",
            "like_number": 1,
            "tweet_source": null,
            "rendered_content": "PEC300, Polícia Militar: O militar digno e o 'clássico da vergonha'. http://ning.it/b7duUI"
        }
    },
    {
        "tweet": {
            "id": 18680661635,
            "creation_date": "2010-07-16 12:13:47",
            "search_type": "User",
            "search_string": "capitao_augusto",
            "like_number": 1,
            "tweet_source": null,
            "rendered_content": "O militar digno e o 'clássico da vergonha': http://congressoemfoco.uol.com.br/noticia.asp?cod_publicacao=33668&cod_canal=4"
        }
    },
    {
        "tweet": {
            "id": 18680461960,
            "creation_date": "2010-07-16 12:10:23",
            "search_type": "User",
            "search_string": "capitao_augusto",
            "like_number": 1,
            "tweet_source": null,
            "rendered_content": "Jornais: 33 candidatos a governador são impugnados: http://congressoemfoco.uol.com.br/noticia.asp?cod_publicacao=33676&cod_canal=1"
        }
    },
    {
        "tweet": {
            "id": 18680320555,
            "creation_date": "2010-07-16 12:08:05",
            "search_type": "User",
            "search_string": "capitao_augusto",
            "like_number": 1,
            "tweet_source": null,
            "rendered_content": "Bom dia a todos!"
        }
    },
    {
        "tweet": {
            "id": 18624557238,
            "creation_date": "2010-07-15 19:07:45",
            "search_type": "User",
            "search_string": "capitao_augusto",
            "like_number": 1,
            "tweet_source": null,
            "rendered_content": "Toshio Misato, Prefeito eleito em Ourinhos apoia Capitão AUGUSTO, confira: www.capitaoaugusto.com.br"
        }
    },
    {
        "tweet": {
            "id": 18624479838,
            "creation_date": "2010-07-15 19:06:24",
            "search_type": "User",
            "search_string": "capitao_augusto",
            "like_number": 1,
            "tweet_source": null,
            "rendered_content": "Em 2008 Ourinhos contava com 71.483 eleitores, separados em 175 sessões e 29 locais de votação."
        }
    },
    {
        "tweet": {
            "id": 18624242379,
            "creation_date": "2010-07-15 19:02:26",
            "search_type": "User",
            "search_string": "capitao_augusto",
            "like_number": 1,
            "tweet_source": null,
            "rendered_content": "Toshio Misato, Prefeito eleito em Ourinhos com quase 74% dos votos, apoia a candidatura do Capitao AUGUSTO e esta confiante em sua vitória"
        }
    },
    {
        "tweet": {
            "id": 18563458502,
            "creation_date": "2010-07-15 01:17:14",
            "search_type": "User",
            "search_string": "capitao_augusto",
            "like_number": 0,
            "tweet_source": null,
            "rendered_content": "@landiosi Muito obrigado pelo apoio Landiosi, Sucesso!"
        }
    },
    {
        "tweet": {
            "id": 18554969880,
            "creation_date": "2010-07-14 22:59:43",
            "search_type": "User",
            "search_string": "capitao_augusto",
            "like_number": 1,
            "tweet_source": null,
            "rendered_content": "@JuGomes_2510 Estou aqui, em que posso ajudar?"
        }
    },
    {
        "tweet": {
            "id": 18522894928,
            "creation_date": "2010-07-14 14:23:41",
            "search_type": "User",
            "search_string": "capitao_augusto",
            "like_number": 0,
            "tweet_source": null,
            "rendered_content": "@Marco_Brasil Olá meu amigo, tudo bem? Estamos na luta e, muito obrigado por me seguir no twitter, Sucesso!"
        }
    },
    {
        "tweet": {
            "id": 18514731954,
            "creation_date": "2010-07-14 12:13:59",
            "search_type": "User",
            "search_string": "capitao_augusto",
            "like_number": 1,
            "tweet_source": null,
            "rendered_content": "R7 vai sabatinar os presidênciaveis enviem suas perguntas sobre a PEC300l.: http://ning.it/akhz4w"
        }
    },
    {
        "tweet": {
            "id": 18514647132,
            "creation_date": "2010-07-14 12:12:24",
            "search_type": "User",
            "search_string": "capitao_augusto",
            "like_number": 1,
            "tweet_source": null,
            "rendered_content": "R7 vai sabatinar os presidênciaveis enviem suas perguntas sobre a PEC300.: http://ning.it/akhz4w"
        }
    },
    {
        "tweet": {
            "id": 18513535412,
            "creation_date": "2010-07-14 11:51:19",
            "search_type": "User",
            "search_string": "capitao_augusto",
            "like_number": 1,
            "tweet_source": null,
            "rendered_content": "Bom dia a todos e que a paz esteja com vocês!"
        }
    },
    {
        "tweet": {
            "id": 18480648254,
            "creation_date": "2010-07-14 01:08:17",
            "search_type": "User",
            "search_string": "capitao_augusto",
            "like_number": 1,
            "tweet_source": null,
            "rendered_content": "Declare seu apoio a nossa candidatura envie texto e foto para assessoria@capitaoaugusto.com.br"
        }
    },
    {
        "tweet": {
            "id": 18478992231,
            "creation_date": "2010-07-14 00:42:23",
            "search_type": "User",
            "search_string": "capitao_augusto",
            "like_number": 1,
            "tweet_source": null,
            "rendered_content": "Conferindo \"R7 fará sabatina com candidatos à Presidência: Portal inicia na \" no Policiais e Bombeiros do Brasil.: http://ning.it/9XqzAT"
        }
    },
    {
        "tweet": {
            "id": 18455366057,
            "creation_date": "2010-07-13 17:59:36",
            "search_type": "User",
            "search_string": "capitao_augusto",
            "like_number": 1,
            "tweet_source": null,
            "rendered_content": "pec300 \"Vila militar para PMs e BMs\" Capitão AUGUSTO.: http://ning.it/dmdUuK"
        }
    },
    {
        "tweet": {
            "id": 18455308632,
            "creation_date": "2010-07-13 17:58:40",
            "search_type": "User",
            "search_string": "capitao_augusto",
            "like_number": 1,
            "tweet_source": null,
            "rendered_content": "PEC300300 \"Saúde para PM e BM\" Capitão AUGUSTO.: http://ning.it/aTbe39"
        }
    },
    {
        "tweet": {
            "id": 18455221289,
            "creation_date": "2010-07-13 17:57:16",
            "search_type": "User",
            "search_string": "capitao_augusto",
            "like_number": 2,
            "tweet_source": null,
            "rendered_content": "pec300 \"Oficial quer benefícios para PMS que atuam à noite\" Capitão AUGUSTO.: http://ning.it/9koSlj"
        }
    },
    {
        "tweet": {
            "id": 18455149173,
            "creation_date": "2010-07-13 17:56:06",
            "search_type": "User",
            "search_string": "capitao_augusto",
            "like_number": 1,
            "tweet_source": null,
            "rendered_content": "pec300 \"Bolsa de estudo para graduação e pós-graduação\" Capitão AUGUSTO: http://ning.it/df4e1Y"
        }
    },
    {
        "tweet": {
            "id": 18455065324,
            "creation_date": "2010-07-13 17:54:45",
            "search_type": "User",
            "search_string": "capitao_augusto",
            "like_number": 1,
            "tweet_source": null,
            "rendered_content": "PEC300\"Limitação de jornada de trabalho para os PM\" Capitão AUGUSTO.: http://ning.it/alShyJ"
        }
    },
    {
        "tweet": {
            "id": 18430617848,
            "creation_date": "2010-07-13 11:46:29",
            "search_type": "User",
            "search_string": "capitao_augusto",
            "like_number": 1,
            "tweet_source": null,
            "rendered_content": "Bom dia a todos e vamos para mais um grande dia na Paz de Deus!"
        }
    },
    {
        "tweet": {
            "id": 18386843852,
            "creation_date": "2010-07-12 22:27:37",
            "search_type": "User",
            "search_string": "capitao_augusto",
            "like_number": 1,
            "tweet_source": null,
            "rendered_content": "121926JUL - Boa noite meus irmãos e irmãs de farda, mais um dia que se finda na certeza do dever cumprido!"
        }
    },
    {
        "tweet": {
            "id": 18373531998,
            "creation_date": "2010-07-12 18:29:37",
            "search_type": "User",
            "search_string": "capitao_augusto",
            "like_number": 0,
            "tweet_source": null,
            "rendered_content": "@fernandocapez Olá amigo, siga-me no twitter, sucesso!"
        }
    },
    {
        "tweet": {
            "id": 18373427035,
            "creation_date": "2010-07-12 18:27:45",
            "search_type": "User",
            "search_string": "capitao_augusto",
            "like_number": 1,
            "tweet_source": null,
            "rendered_content": "Polícial vota em Polícial, adote esta idéia, vote consciente. Declare seu apoio acesse: www.capitaoaugusto.com.br"
        }
    },
    {
        "tweet": {
            "id": 18349357080,
            "creation_date": "2010-07-12 12:07:42",
            "search_type": "User",
            "search_string": "capitao_augusto",
            "like_number": 1,
            "tweet_source": null,
            "rendered_content": "Bom dia a todos, com a Graça de Deus mais uma semana de muito trabalho na Paz de Nosso Senhor Jesus Cristo."
        }
    },
    {
        "tweet": {
            "id": 18308090874,
            "creation_date": "2010-07-11 22:23:12",
            "search_type": "User",
            "search_string": "capitao_augusto",
            "like_number": 0,
            "tweet_source": null,
            "rendered_content": "@capitaoassumcao Abraço e que Deus nos ilumine nesta nova empreitada em prol dos PMs, BMs e do Povo Brasileiro."
        }
    },
    {
        "tweet": {
            "id": 18307457107,
            "creation_date": "2010-07-11 22:12:09",
            "search_type": "User",
            "search_string": "capitao_augusto",
            "like_number": 1,
            "tweet_source": null,
            "rendered_content": "@capitaoassumcao Conte comigo também, estou a sua inteira disposição qq (14) 9697.1139"
        }
    },
    {
        "tweet": {
            "id": 18307283929,
            "creation_date": "2010-07-11 22:09:12",
            "search_type": "User",
            "search_string": "capitao_augusto",
            "like_number": 0,
            "tweet_source": null,
            "rendered_content": "@capitaoassumcao Abraço meu irmão e Sucesso!"
        }
    }
]